assess_acceptability_judgments/__init__.py
assess_acceptability_judgments/constituency_parser.py
assess_acceptability_judgments/core_nlp_parser_interface.py
assess_acceptability_judgments/dependency_parser.py
assess_acceptability_judgments/fluency_score_interface.py
assess_acceptability_judgments/nce.py
assess_acceptability_judgments/ppl.py
assess_acceptability_judgments/ressources.py
assess_acceptability_judgments/slor.py
assess_acceptability_judgments/util.py
assess_acceptability_judgments/version.py
assess_acceptability_judgments/resources/conll_u_tags_mapping.json
assess_acceptability_judgments/resources/treebank_tags_mapping.json
assess_acceptability_judgments/resources/nce_scores_distribution/treebank.json
assess_acceptability_judgments/resources/nce_scores_distribution/whitespace.json
assess_acceptability_judgments/resources/nce_scores_distribution/whitespace_llm_bert_base_uncased.json
assess_acceptability_judgments/resources/nce_scores_distribution/whitespace_llm_bert_large_uncased.json
assess_acceptability_judgments/resources/nce_scores_distribution/whitespace_llm_roberta_base.json
assess_acceptability_judgments/resources/nce_scores_distribution/wordpiece_bert_base_uncased.json
assess_acceptability_judgments/resources/nce_scores_distribution/wordpiece_bert_large_uncased.json
assess_acceptability_judgments/resources/nce_scores_distribution/wordpiece_roberta_base.json
assess_acceptability_judgments/resources/slor_scores_distribution/treebank.json
assess_acceptability_judgments/resources/slor_scores_distribution/whitespace.json
assess_acceptability_judgments/resources/slor_scores_distribution/whitespace_llm_bert_base_uncased.json
assess_acceptability_judgments/resources/slor_scores_distribution/whitespace_llm_bert_large_uncased.json
assess_acceptability_judgments/resources/slor_scores_distribution/whitespace_llm_roberta_base.json
assess_acceptability_judgments/resources/slor_scores_distribution/wordpiece_bert_base_uncased.json
assess_acceptability_judgments-0.0.28.dist-info/LICENSE
assess_acceptability_judgments-0.0.28.dist-info/METADATA
assess_acceptability_judgments-0.0.28.dist-info/WHEEL
assess_acceptability_judgments-0.0.28.dist-info/top_level.txt
assess_acceptability_judgments-0.0.28.dist-info/RECORD
