Metadata-Version: 2.1
Name: assess-acceptability-judgments
Version: 0.0.28
Summary: A library for assessing acceptability judgments
Home-page: https://github.com/davebulaval/assess_acceptability_judgments
Download-URL: https://github.com/GRAAL-Research/assess_acceptability_judgments/archive/v0.0.28.zip
Author: David Beauchemin
Author-email: david.beauchemin.5@ulaval.ca
License: LGPLv3
Classifier: Development Status :: 3 - Alpha
Classifier: Intended Audience :: Developers
Classifier: Intended Audience :: Education
Classifier: Intended Audience :: Science/Research
Classifier: License :: OSI Approved :: GNU Lesser General Public License v3 (LGPLv3)
Classifier: Programming Language :: Python :: 3
Classifier: Programming Language :: Python :: 3.8
Classifier: Programming Language :: Python :: 3.9
Classifier: Programming Language :: Python :: 3.10
Classifier: Programming Language :: Python :: 3.11
Classifier: Topic :: Software Development :: Libraries
Classifier: Topic :: Software Development :: Libraries :: Python Modules
Classifier: Topic :: Scientific/Engineering
Classifier: Topic :: Scientific/Engineering :: Artificial Intelligence
Requires-Python: >=3.8
License-File: LICENSE
Requires-Dist: transformers
Requires-Dist: torch
Requires-Dist: numpy
Requires-Dist: nltk
Requires-Dist: stanza
Requires-Dist: supar
Requires-Dist: benepar
Requires-Dist: spacy
Requires-Dist: spacy-transformers
Requires-Dist: progressbar
Requires-Dist: conllu
Requires-Dist: tqdm
